{
  "publicPath": "/_nuxt/",
  "all": [
    "../server/index.spa.html",
    "../server/index.ssr.html",
    "06b9a76.js",
    "23b10b6.js",
    "355cf78.js",
    "64a1bce.js",
    "6e7d9b9.js",
    "89b7004.js",
    "LICENSES",
    "a1b774e.js",
    "bffa629.js",
    "d855302.js",
    "dc041f8.js",
    "ec50736.js"
  ],
  "initial": [
    "6e7d9b9.js",
    "bffa629.js",
    "64a1bce.js"
  ],
  "async": [
    "06b9a76.js",
    "23b10b6.js",
    "355cf78.js",
    "89b7004.js",
    "a1b774e.js",
    "d855302.js",
    "dc041f8.js",
    "ec50736.js"
  ],
  "modules": {
    "11517304": [
      10
    ],
    "23927366": [
      10
    ],
    "46383756": [
      10
    ],
    "53379960": [
      10
    ],
    "80038256": [
      10
    ],
    "97015ad0": [
      5
    ],
    "1e9e03ab": [
      10
    ],
    "bed2eaa0": [
      10
    ],
    "03412c7a": [
      5
    ],
    "c2ee3f3e": [
      10
    ],
    "83a1feaa": [
      10
    ],
    "1265c074": [
      10
    ],
    "b1b80816": [
      10
    ],
    "2ad45396": [
      10
    ],
    "2304e483": [
      5
    ],
    "7908370b": [
      5
    ],
    "5c573410": [
      5
    ],
    "64bd50f0": [
      5
    ],
    "4a83357c": [
      5
    ],
    "50d18611": [
      5
    ],
    "9944ac60": [
      10
    ],
    "3798ad30": [
      10
    ],
    "918c3194": [
      10
    ],
    "88263d9e": [
      10
    ],
    "3805ec72": [
      10
    ],
    "68d995e2": [
      5
    ],
    "65f0c6eb": [
      5
    ],
    "faf0fb66": [
      10
    ],
    "5cec050e": [
      10
    ],
    "e0b98a52": [
      5
    ],
    "c1fbc548": [
      5
    ],
    "570b3791": [
      5
    ],
    "5c8109a5": [
      5
    ],
    "70c46c80": [
      5
    ],
    "cc279870": [
      5
    ],
    "216f8730": [
      5
    ],
    "6188f29b": [
      5
    ],
    "4e2a3636": [
      5
    ],
    "3d6a9207": [
      5
    ],
    "338d4eac": [
      5
    ],
    "92879cce": [
      5
    ],
    "6b07880f": [
      5
    ],
    "7b18347e": [
      5
    ],
    "12e4ff4b": [
      5
    ],
    "4fca03c7": [
      5
    ],
    "8103ce94": [
      5
    ],
    "71334d76": [
      5
    ],
    "07907093": [
      5
    ],
    "4d6c048c": [
      5
    ],
    "cbcb6270": [
      10
    ],
    "cbf98bb6": [
      10
    ],
    "d0fff4bc": [
      10
    ],
    "3ea46098": [
      10
    ],
    "912bc0e4": [
      5
    ],
    "04786750": [
      10
    ],
    "06a0e720": [
      10
    ],
    "06039eba": [
      10
    ],
    "93766bb0": [
      10
    ],
    "357a0d0e": [
      10
    ],
    "399ce9d4": [
      10
    ],
    "cc95c400": [
      10
    ],
    "b4f04e6c": [
      10
    ],
    "291ce001": [
      10
    ],
    "3bb2c184": [
      10
    ],
    "350db613": [
      10
    ],
    "7dff6eec": [
      10
    ],
    "4e70c166": [
      10
    ],
    "582dfba6": [
      10
    ],
    "15cbc0a2": [
      10
    ],
    "17f47838": [
      5
    ],
    "53b18ac2": [
      10
    ],
    "0420c77e": [
      10
    ],
    "1b1151da": [
      10
    ],
    "439f440f": [
      10
    ],
    "11828cf8": [
      10
    ],
    "66f19cb4": [
      10
    ],
    "60f6ee05": [
      10
    ],
    "7e367dab": [
      10
    ],
    "c054b762": [
      10
    ],
    "19898c14": [
      10
    ],
    "1992a380": [
      10
    ],
    "2924685f": [
      10
    ],
    "33d7d220": [
      10
    ],
    "b8579ef6": [
      10
    ],
    "1985005e": [
      10
    ],
    "5560f6fb": [
      10
    ],
    "3cef05e6": [
      10
    ],
    "759c47b6": [
      10
    ],
    "e783f46c": [
      10
    ],
    "0bc445f2": [
      10
    ],
    "228d2783": [
      10
    ],
    "6921de50": [
      10
    ],
    "1cde590e": [
      5
    ],
    "4554b0ef": [
      10
    ],
    "2db4d1c6": [
      10
    ],
    "aa7152ce": [
      10
    ],
    "3f296cc2": [
      10
    ],
    "fba79fe6": [
      10
    ],
    "61e0ccd1": [
      10
    ],
    "69da2ca1": [
      10
    ],
    "d27ea47e": [
      10
    ],
    "6533ad11": [
      10
    ],
    "3b17e75e": [
      10
    ],
    "6de9a6d6": [
      10
    ],
    "475e6103": [
      10
    ],
    "a9a72b96": [
      10
    ],
    "404684a2": [
      10
    ],
    "582ca3a7": [
      10
    ],
    "4fc2ff05": [
      5
    ],
    "89d0991a": [
      5
    ],
    "7d439af6": [
      5
    ],
    "9db767cc": [
      10
    ],
    "0a47a331": [
      5
    ],
    "c0abf640": [
      10
    ],
    "753e7a0d": [
      10
    ],
    "dde5bcc8": [
      10
    ],
    "d348ab52": [
      10
    ],
    "4d8fc6bc": [
      10
    ],
    "3c813bc5": [
      10
    ],
    "3318e824": [
      10
    ],
    "a89765d2": [
      10
    ],
    "5bddfb7b": [
      10
    ],
    "4e531b38": [
      10
    ],
    "d3edd61e": [
      10
    ],
    "61cce732": [
      10
    ],
    "8aaad4bc": [
      10
    ],
    "f0a51bca": [
      10
    ],
    "f6c585cc": [
      10
    ],
    "057a227f": [
      10
    ],
    "3bc8f32d": [
      10
    ],
    "5baa2e30": [
      10
    ],
    "61058e8e": [
      10
    ],
    "5a824b6c": [
      10
    ],
    "2c823436": [
      10
    ],
    "5d8c00e0": [
      10
    ],
    "04698c1b": [
      10
    ],
    "0d0dfbfc": [
      10
    ],
    "12b4cc8e": [
      10
    ],
    "7b49ff72": [
      5
    ],
    "2f9a040a": [
      5
    ],
    "41c5da3e": [
      5
    ],
    "f63e01d8": [
      10
    ],
    "20d650a0": [
      10
    ],
    "00d38340": [
      10
    ],
    "7c974894": [
      10
    ],
    "462d1044": [
      10
    ],
    "27e0ae39": [
      10
    ],
    "3f35a76a": [
      10
    ],
    "db2bf8ec": [
      10
    ],
    "6a605518": [
      5
    ],
    "20b34531": [
      5
    ],
    "dcf67fd6": [
      5
    ],
    "0be12bcd": [
      5
    ],
    "0e1f31d3": [
      5
    ],
    "2ae42db0": [
      10
    ],
    "456daeff": [
      5
    ],
    "4ccfc8bd": [
      10
    ],
    "11ff8352": [
      5
    ],
    "db6b3080": [
      5
    ],
    "2371b08d": [
      10
    ],
    "6a4c1b70": [
      5
    ],
    "2378599a": [
      5
    ],
    "df35e694": [
      10
    ],
    "cbe91c02": [
      10
    ],
    "e8fb6eca": [
      10
    ],
    "1d920aaa": [
      10
    ],
    "8f13e82a": [
      10
    ],
    "5ce279bc": [
      10
    ],
    "1a2341e9": [
      10
    ],
    "16e0bb8e": [
      10
    ],
    "84da7768": [
      10
    ],
    "20dc0064": [
      10
    ],
    "f22740ae": [
      10
    ],
    "1fd8736c": [
      10
    ],
    "7063f9fe": [
      10
    ],
    "424c90ae": [
      10
    ],
    "53343b01": [
      10
    ],
    "2f169e3c": [
      10
    ],
    "c61ff3ea": [
      10
    ],
    "5ee587e6": [
      10
    ],
    "0076d178": [
      10
    ],
    "73f46be3": [
      10
    ],
    "ca3b2faa": [
      5
    ],
    "57416cb8": [
      5
    ],
    "396d6de9": [
      10
    ],
    "018d5225": [
      10
    ],
    "b862b796": [
      10
    ],
    "4d159bb3": [
      10
    ],
    "7f7c6eda": [
      10
    ],
    "b33bb9a0": [
      10
    ],
    "0a47afe6": [
      10
    ],
    "3c37b7c3": [
      10
    ],
    "f1f12f9e": [
      10
    ],
    "8ab6c39a": [
      10
    ],
    "8033a8fa": [
      10
    ],
    "f3ef9ae6": [
      10
    ],
    "24abc876": [
      10
    ],
    "3d18a872": [
      10
    ],
    "fc2a1538": [
      5
    ],
    "4260de57": [
      5
    ],
    "24011bb0": [
      5
    ],
    "c2bed83a": [
      5
    ],
    "0ba90827": [
      5
    ],
    "627d44cc": [
      10
    ],
    "5d4fae10": [
      10
    ],
    "28f60a8f": [
      10
    ],
    "a9dfa5be": [
      10
    ],
    "e95da760": [
      10
    ],
    "3f6298a2": [
      10
    ],
    "2fdecf10": [
      10
    ],
    "f8d63c44": [
      10
    ],
    "9dcbe162": [
      10
    ],
    "20e67f64": [
      10
    ],
    "f2d934fa": [
      10
    ],
    "2f74d5e2": [
      10
    ],
    "004fec9a": [
      10
    ],
    "d3eb4784": [
      10
    ],
    "1c527cac": [
      10
    ],
    "5438a06a": [
      10
    ],
    "5869e79e": [
      10
    ],
    "72fb5e16": [
      10
    ],
    "962cd0ca": [
      7
    ],
    "10f2fc54": [
      7
    ],
    "0b82409d": [
      7
    ],
    "c7aee68c": [
      7
    ],
    "7d23780c": [
      9
    ],
    "059f1cd2": [
      9
    ],
    "980d52fe": [
      7
    ],
    "a40f0a0a": [
      7
    ],
    "7606a8ba": [
      7
    ],
    "38eeb7f2": [
      7
    ],
    "fb3625e8": [
      7
    ],
    "3a462805": [
      7
    ],
    "1f20fffa": [
      7
    ],
    "3c496ddc": [
      7
    ],
    "02ba0c16": [
      9
    ],
    "6f0da3f5": [
      9
    ],
    "38ec98f0": [
      9
    ],
    "91e9136c": [
      7
    ],
    "36aff97e": [
      7
    ],
    "21e5fdf5": [
      7
    ],
    "c9a4a86a": [
      7
    ],
    "5ffea8f3": [
      7
    ],
    "a578cb6c": [
      7
    ],
    "23df9d0c": [
      7
    ],
    "58685beb": [
      7
    ],
    "15cb0b4f": [
      7
    ],
    "8d612a90": [
      7
    ],
    "225cb82e": [
      7
    ],
    "234327e2": [
      7
    ],
    "17b8d3f6": [
      7
    ],
    "ea7fd510": [
      7
    ],
    "700d6798": [
      7
    ],
    "7205ee7a": [
      7
    ],
    "1d71d07a": [
      7
    ],
    "fdebeb36": [
      7
    ],
    "6e1965a4": [
      7
    ],
    "6f98821d": [
      7
    ],
    "ac236fa0": [
      7
    ],
    "6dc4b671": [
      7
    ],
    "2b7c7b8e": [
      7
    ],
    "78ed3b7c": [
      7
    ],
    "adc63b12": [
      7
    ],
    "9b9def8e": [
      7
    ],
    "0c581d55": [
      7
    ],
    "3b53517a": [
      7
    ],
    "7bd21626": [
      7
    ],
    "3227e95f": [
      7
    ],
    "6757442b": [
      7
    ],
    "5f3d695c": [
      7
    ],
    "691eb7f0": [
      7
    ],
    "48150da4": [
      7
    ],
    "151f085c": [
      7
    ],
    "330827ea": [
      7
    ],
    "e4fdc00c": [
      7
    ],
    "3257ed0b": [
      7
    ],
    "221eece2": [
      7
    ],
    "f2a2a612": [
      7
    ],
    "2a523ae7": [
      7
    ],
    "dd2f19c4": [
      7
    ],
    "214c177b": [
      7
    ],
    "2f59ebe2": [
      7
    ],
    "536f8aa9": [
      7
    ],
    "107af655": [
      7
    ],
    "298e3a40": [
      7
    ],
    "7a7e8652": [
      7
    ],
    "7a0394f1": [
      7
    ],
    "3d4335f9": [
      7
    ],
    "b1b3198e": [
      7
    ],
    "0387ebd3": [
      7
    ],
    "31e55561": [
      7
    ],
    "c2e9884c": [
      7
    ],
    "1cdff5ea": [
      7
    ],
    "0c3ab97b": [
      7
    ],
    "899c22c0": [
      11
    ],
    "23dccbbe": [
      11
    ],
    "16d703e2": [
      11
    ],
    "9fd211fc": [
      11
    ],
    "0ffc962c": [
      11
    ],
    "7fa4b060": [
      11
    ],
    "de066282": [
      11
    ],
    "58f7eaad": [
      11
    ],
    "2003b45f": [
      11
    ],
    "57a76070": [
      11
    ],
    "74aa6350": [
      11
    ],
    "4a5f4cf1": [
      11
    ],
    "76e2df3c": [
      11
    ],
    "22d0f00c": [
      11
    ],
    "bfe250a6": [
      11
    ],
    "489a3dc8": [
      3
    ],
    "6f27936e": [
      3
    ],
    "5dec6202": [
      3
    ],
    "2118efaa": [
      3
    ],
    "bf40817c": [
      3
    ],
    "7e6ce591": [
      9
    ],
    "7528f907": [
      9
    ],
    "946eb4ac": [
      9
    ],
    "4efc3443": [
      9
    ],
    "89586aa6": [
      9
    ],
    "26c11453": [
      13
    ],
    "089f817b": [
      13
    ],
    "0b1f2b88": [
      13
    ],
    "6933adbf": [
      13
    ],
    "b36c34ce": [
      13
    ],
    "b554b0da": [
      12
    ],
    "22ef4ed0": [
      12
    ],
    "c64ca708": [
      12
    ],
    "a1ad0bd8": [
      12
    ],
    "8f7c76ce": [
      12
    ],
    "499dd5d5": [
      2
    ],
    "44ffa510": [
      2
    ],
    "d8232234": [
      2
    ],
    "4ee92a98": [
      2
    ],
    "34ed4b2e": [
      2
    ],
    "1df160c2": [
      4
    ],
    "42f3a308": [
      4
    ],
    "13baac48": [
      4
    ],
    "df10ea90": [
      4
    ],
    "750ecbc2": [
      4
    ]
  },
  "assetsMapping": {
    "bba68bf6": [
      "06b9a76.js",
      "23b10b6.js",
      "355cf78.js",
      "89b7004.js",
      "a1b774e.js",
      "d855302.js",
      "dc041f8.js",
      "ec50736.js"
    ],
    "1a3ae26b": [
      "64a1bce.js"
    ],
    "6fca0322": [
      "6e7d9b9.js"
    ],
    "085a35c4": [
      "bffa629.js"
    ]
  }
}